ami_organizer-0.1.1.dist-info/DESCRIPTION.rst
ami_organizer-0.1.1.dist-info/entry_points.txt
ami_organizer-0.1.1.dist-info/METADATA
ami_organizer-0.1.1.dist-info/metadata.json
ami_organizer-0.1.1.dist-info/RECORD
ami_organizer-0.1.1.dist-info/top_level.txt
ami_organizer-0.1.1.dist-info/WHEEL
amiorganizer/__init__.py
amiorganizer/app_config.py
amiorganizer/AppConfig.py
amiorganizer/application.py
amiorganizer/errors/__init__.py
amiorganizer/errors/Errors.py
amiorganizer/util/__init__.py
amiorganizer/util/log.py
amiorganizer/util/utils.py
