Metadata-Version: 2.0
Name: ami-organizer
Version: 0.1.1
Summary: An AMI creator and cataloging system
Home-page: https://github.com/samkeen/ami-organizer
Author: Sam Keen
Author-email: sam.sjk@gmail.com
License: UNKNOWN
Download-URL: https://github.com/samkeen/ami-organizer/archive/v0.1.1.tar.gz
Keywords: ami,aws,ec2
Platform: UNKNOWN
Classifier: Development Status :: 3 - Alpha
Classifier: Intended Audience :: Developers
Classifier: Environment :: Console
Classifier: Natural Language :: English
Classifier: Topic :: Utilities
Classifier: License :: OSI Approved :: MIT License
Classifier: Programming Language :: Python :: 2
Classifier: Programming Language :: Python :: 2.7
Classifier: Programming Language :: Python :: 3
Classifier: Programming Language :: Python :: 3.5
Requires-Dist: Click
Requires-Dist: pytz
Requires-Dist: PyYAML
